{"id":"digital-1","title":"Мой первый BankID","level":"A2","category":"society","topic":"digital_services","length":"short","description":"Как я получила электронную идентификацию в Норвегии","segments":[{"type":"ru","text":"Когда я ","no":"Da jeg "},{"type":"no","text":"åpnet","translation":"открыла","dict":"открывать","transcription":"опнэт","pos":"verb"},{"type":"ru","text":" ","no":" "},{"type":"no","text":"bankkonto","translation":"банковский счёт","transcription":"банкконту","pos":"noun"},{"type":"ru","text":", я ","no":", "},{"type":"no","text":"fikk","translation":"получила","dict":"получить","transcription":"фикк","pos":"verb"},{"type":"ru","text":" ","no":" "},{"type":"no","text":"BankID","translation":"БанкАйДи","transcription":"банкайди","pos":"noun"},{"type":"ru","text":". Это ","no":". Det er en "},{"type":"no","text":"elektronisk identifikasjon","translation":"электронная идентификация","dict":"электронная идентификация","transcription":"элэктуниск идэнтификасьон","pos":"phrase"},{"type":"ru","text":". Без неё ничего нельзя ","no":". Uten den kan man ikke "},{"type":"no","text":"gjøre","translation":"сделать","dict":"делать","transcription":"йёрэ","pos":"verb"},{"type":"ru","text":" ","no":" noe "},{"type":"no","text":"på nett","translation":"онлайн","transcription":"по нэтт","pos":"phrase"},{"type":"ru","text":". Сначала я ","no":". Først "},{"type":"no","text":"fikk","translation":"получила","dict":"получить","transcription":"фикк","pos":"verb"},{"type":"ru","text":" ","no":" jeg et "},{"type":"no","text":"brukernavn","translation":"логин","transcription":"брюкернавн","pos":"noun"},{"type":"ru","text":" и ","no":" og et "},{"type":"no","text":"passord","translation":"пароль","transcription":"пассорд","pos":"noun"},{"type":"ru","text":". Потом я ","no":". Så "},{"type":"no","text":"lastet ned","translation":"скачала","dict":"скачивать","transcription":"ластэт нэд","pos":"verb"},{"type":"ru","text":" ","no":" jeg "},{"type":"no","text":"appen","translation":"приложение","dict":"приложение","transcription":"аппэн","pos":"noun"},{"type":"ru","text":" на ","no":" på "},{"type":"no","text":"mobilen","translation":"телефон","dict":"телефон","transcription":"мубилен","pos":"noun"},{"type":"ru","text":". Теперь я могу ","no":". Nå kan jeg "},{"type":"no","text":"logge inn","translation":"входить","dict":"войти","transcription":"логгэ инн","pos":"verb"},{"type":"ru","text":" в ","no":" på "},{"type":"no","text":"nettbank","translation":"интернет-банк","transcription":"нэттбанк","pos":"noun"},{"type":"ru","text":", ","no":", "},{"type":"no","text":"Skatteetaten","translation":"Налоговую службу","transcription":"скаттээтатэн","pos":"noun"},{"type":"ru","text":" и другие ","no":" og andre "},{"type":"no","text":"tjenester","translation":"сервисы","dict":"услуга","transcription":"тьенэстэр","pos":"noun"},{"type":"ru","text":". Это очень ","no":". Det er veldig "},{"type":"no","text":"praktisk","translation":"удобно","transcription":"практиск","pos":"adj"},{"type":"ru","text":" и ","no":" og "},{"type":"no","text":"trygt","translation":"безопасно","transcription":"трюгт","pos":"adj"},{"type":"ru","text":".","no":"."}]}