{"id":"festival-1","title":"Праздники в Норвегии","titleNo":"Høytider i Norge","level":"A2","category":"culture","topic":"festivals","length":"short","description":"Главные норвежские праздники простыми словами","segments":[{"type":"ru","text":"В Норвегии много ","no":"I Norge er det mange "},{"type":"no","text":"høytider","translation":"праздников","dict":"høytid","transcription":"хёйтидэр","pos":"noun"},{"type":"ru","text":". Самый главный — ","no":". Den viktigste er "},{"type":"ru","text":"17. mai","no":"17. mai"},{"type":"ru","text":". Это национальный праздник. Дети идут с ","no":". Det er nasjonaldagen. Barn går med "},{"type":"no","text":"flagg","translation":"флагами","transcription":"флагг","pos":"noun"},{"type":"ru","text":" по улицам. Зимой норвежцы празднуют ","no":" i gatene. Om vinteren feirer nordmenn "},{"type":"no","text":"jul","translation":"Рождество","transcription":"юль","pos":"noun"},{"type":"ru","text":". Семья собирается дома, едят вкусную еду и дарят ","no":". Familien samles hjemme, spiser god mat og gir "},{"type":"no","text":"gaver","translation":"подарки","dict":"gave","transcription":"гавэр","pos":"noun"},{"type":"ru","text":". Весной — ","no":". Om våren er det "},{"type":"no","text":"påske","translation":"Пасха","transcription":"поске","pos":"noun"},{"type":"ru","text":". Многие едут в горы и катаются на лыжах. Летом норвежцы празднуют ","no":". Mange drar til fjells og går på ski. Om sommeren feirer nordmenn "},{"type":"ru","text":"midtsommer","no":"midtsommer"},{"type":"ru","text":", который называется ","no":", som kalles "},{"type":"ru","text":"sankthans","no":"sankthans"},{"type":"ru","text":". Люди ","no":". Folk "},{"type":"no","text":"tenner bål","translation":"разжигают костры","dict":"разжигать костёр","transcription":"тэннэр бол","pos":"phrase"},{"type":"ru","text":" у моря. Все ","no":" ved sjøen. Alle "},{"type":"no","text":"er glade","translation":"радуются","dict":"радоваться","transcription":"эр гладэ","pos":"phrase"},{"type":"ru","text":" и поют песни. Праздники — важная часть года.","no":" og synger sanger. Høytidene er en viktig del av året."}]}
